NEMO_user_chemicals/__init__.py
NEMO_user_chemicals/admin.py
NEMO_user_chemicals/apps.py
NEMO_user_chemicals/customizations.py
NEMO_user_chemicals/forms.py
NEMO_user_chemicals/models.py
NEMO_user_chemicals/tests.py
NEMO_user_chemicals/urls.py
NEMO_user_chemicals/views.py
NEMO_user_chemicals/migrations/0001_initial.py
NEMO_user_chemicals/migrations/0002_chemicallocation_remove_chemicalrequest_corrosive_and_more.py
NEMO_user_chemicals/migrations/0003_remove_chemicalrequest_health_hazards.py
NEMO_user_chemicals/migrations/0004_userchemical_trade_name.py
NEMO_user_chemicals/migrations/0005_remove_userchemical_trade_name_and_more.py
NEMO_user_chemicals/migrations/0006_userchemical_trade_name.py
NEMO_user_chemicals/migrations/0007_rename_chemical_name_chemicalrequest_name_and_more.py
NEMO_user_chemicals/migrations/0008_userchemical_history.py
NEMO_user_chemicals/migrations/0009_alter_chemicalrequest_cas.py
NEMO_user_chemicals/migrations/__init__.py
NEMO_user_chemicals/templates/NEMO_user_chemicals/add_chemical.html
NEMO_user_chemicals/templates/NEMO_user_chemicals/add_user_chemical.html
NEMO_user_chemicals/templates/NEMO_user_chemicals/ajax_base.html
NEMO_user_chemicals/templates/NEMO_user_chemicals/chemical_request.html
NEMO_user_chemicals/templates/NEMO_user_chemicals/dashboard.html
NEMO_user_chemicals/templates/NEMO_user_chemicals/request_details.html
NEMO_user_chemicals/templates/NEMO_user_chemicals/request_update.html
NEMO_user_chemicals/templates/NEMO_user_chemicals/update_user_chemical.html
NEMO_user_chemicals/templates/NEMO_user_chemicals/user_chemicals.html
NEMO_user_chemicals/templates/NEMO_user_chemicals/view_requests.html
NEMO_user_chemicals/templates/NEMO_user_chemicals/customizations/customizations_chemicals.html
nemo_user_chemicals-2.1.0.dist-info/licenses/LICENSE
nemo_user_chemicals-2.1.0.dist-info/METADATA
nemo_user_chemicals-2.1.0.dist-info/WHEEL
nemo_user_chemicals-2.1.0.dist-info/top_level.txt
nemo_user_chemicals-2.1.0.dist-info/RECORD
