Metadata-Version: 2.4
Name: NEMO-user-chemicals
Version: 2.1.0
Summary: User chemical request and inventory management plugin for NEMO
Home-page: https://gitlab.com/nemo-community/upenn/nemo_user_chemicals
Author: David Barth
Author-email: dsbarth@seas.upenn.edu
Keywords: NEMO
License-File: LICENSE
Requires-Dist: django
Provides-Extra: nemo
Requires-Dist: NEMO>=7.0.0; extra == "nemo"
Provides-Extra: dev-tools
Requires-Dist: pre-commit; extra == "dev-tools"
Requires-Dist: djlint; extra == "dev-tools"
Requires-Dist: black; extra == "dev-tools"
Dynamic: author
Dynamic: author-email
Dynamic: home-page
Dynamic: keywords
Dynamic: license-file
Dynamic: provides-extra
Dynamic: requires-dist
Dynamic: summary
